lido_validate_keys.py
setup.py
lido_cli-2.1.0.dist-info/entry_points.txt
lido_cli-2.1.0.dist-info/LICENSE
lido_cli-2.1.0.dist-info/WHEEL
lido_cli-2.1.0.dist-info/METADATA
lido_cli-2.1.0.dist-info/RECORD
