Metadata-Version: 2.1
Name: lido-cli
Version: 2.1.0
Summary: Lido CLI tool for node operator key validation
Home-page: https://lido.fi
License: MIT
Author: Lido
Author-email: info@lido.fi
Requires-Python: >3.7.1,<4
Classifier: License :: OSI Approved :: MIT License
Classifier: Programming Language :: Python :: 3
Classifier: Programming Language :: Python :: 3.8
Classifier: Programming Language :: Python :: 3.9
Requires-Dist: click (==8.0.1)
Requires-Dist: colorama (==0.4.4)
Requires-Dist: lido-sdk (==2.2.1)
Project-URL: Repository, https://github.com/lidofinance/lido-node-operator-key-checker-cli
